README.rst
setup.py
sqlitelist/__init__.py
sqlitelist/tests.py
sqlitelist/wrapper.py
sqlitelist.egg-info/PKG-INFO
sqlitelist.egg-info/SOURCES.txt
sqlitelist.egg-info/dependency_links.txt
sqlitelist.egg-info/top_level.txt