Metadata-Version: 1.1
Name: sqlitelist
Version: 0.1
Summary: SQLite3 wrapper with a list-like interface
Home-page: UNKNOWN
Author: deliro
Author-email: t4k.kitaetz@gmail.com
License: Apache 2.0
Platform: UNKNOWN
Classifier: Development Status :: 4 - Beta
Classifier: Intended Audience :: Developers
Classifier: Natural Language :: English
Classifier: License :: OSI Approved :: Apache Software License
Classifier: Programming Language :: Python
Classifier: Programming Language :: Python :: 3
Classifier: Programming Language :: Python :: 3.3
Classifier: Programming Language :: Python :: 3.4
